[
    {
        "name": "MR S D DAWSON",
        "email": "siondawson91@gmail.com",
        "phone": "07792091467",
        "message": "dropbox",
        "submitted_at": "2024-11-01T17:13:11.116615",
        "converted": false
    },
    {
        "name": "JANE DOE",
        "email": "janedoe@example.com",
        "phone": "07712345678",
        "message": "Testing Dropbox integration.",
        "submitted_at": "2024-11-01T17:13:11.116631",
        "converted": false
    },
    {
        "name": "JOHN SMITH",
        "email": "johnsmith@example.com",
        "phone": "07787654321",
        "message": "This is a test message.",
        "submitted_at": "2024-11-01T17:13:11.116636",
        "converted": false
    }
]
